{ "compressionlevel":-1,
 "editorsettings":
    {
     "export":
        {
         "format":"json",
         "target":"readyRoom.json"
        }
    },
 "height":10,
 "infinite":false,
 "layers":[
        {
         "draworder":"topdown",
         "id":2,
         "name":"sensor_layer",
         "objects":[
                {
                 "height":59.949119649526,
                 "id":4,
                 "name":"blue_team_ready_zone",
                 "properties":[
                        {
                         "name":"team",
                         "type":"string",
                         "value":"red"
                        }],
                 "rotation":0,
                 "type":"sensor",
                 "visible":true,
                 "width":58.3998850904912,
                 "x":252.852682275208,
                 "y":75.2908754380925
                }, 
                {
                 "height":39.6722,
                 "id":8,
                 "name":"exit_room_zone",
                 "rotation":0,
                 "type":"",
                 "visible":true,
                 "width":33.9693,
                 "x":-3.30189,
                 "y":93.3467
                }, 
                {
                 "height":59.9491,
                 "id":17,
                 "name":"red_team_ready_zone",
                 "properties":[
                        {
                         "name":"team",
                         "type":"string",
                         "value":"blue"
                        }],
                 "rotation":0,
                 "type":"sensor",
                 "visible":true,
                 "width":54.9526147371445,
                 "x":107.542365426602,
                 "y":75.742198060902
                }],
         "opacity":1,
         "type":"objectgroup",
         "visible":true,
         "x":0,
         "y":0
        }, 
        {
         "draworder":"topdown",
         "id":5,
         "name":"info_layer",
         "objects":[
                {
                 "height":0,
                 "id":7,
                 "name":"red_team_spawn_point",
                 "point":true,
                 "rotation":0,
                 "type":"",
                 "visible":true,
                 "width":0,
                 "x":207.148271042804,
                 "y":92.4187950876185
                }, 
                {
                 "height":0,
                 "id":21,
                 "name":"blue_team_spawn_point",
                 "point":true,
                 "rotation":0,
                 "type":"",
                 "visible":true,
                 "width":0,
                 "x":206.262568227521,
                 "y":92.5021545532893
                }],
         "opacity":1,
         "type":"objectgroup",
         "visible":true,
         "x":0,
         "y":0
        }, 
        {
         "data":[0, 0, 0, 0, 0, 0, 0, 0, 0, 0, 0, 0, 0, 0, 0, 0, 0, 0, 0, 0, 0, 0, 0, 0, 0, 0, 0, 0, 0, 0, 0, 0, 0, 0, 0, 0, 0, 0, 0, 0, 0, 0, 0, 0, 0, 0, 0, 0, 0, 0, 0, 0, 0, 0, 0, 0, 0, 0, 0, 0, 0, 0, 0, 0, 0, 0, 0, 0, 0, 0, 0, 0, 0, 0, 0, 0, 0, 0, 0, 0, 0, 0, 0, 0, 0, 0, 30, 31, 31, 31, 32, 0, 0, 0, 0, 30, 31, 31, 31, 32, 25, 26, 0, 0, 0, 0, 38, 36, 44, 37, 40, 0, 0, 0, 0, 38, 36, 28, 28, 40, 33, 34, 0, 0, 0, 0, 38, 45, 37, 36, 35, 0, 0, 0, 0, 2147483683, 44, 28, 36, 40, 0, 0, 34, 0, 0, 0, 38, 44, 28, 37, 35, 0, 0, 0, 0, 2147483683, 28, 29, 45, 40, 31, 31, 31, 31, 31, 31, 31, 31, 31, 31, 31, 31, 31, 31, 31, 31, 31, 31, 31, 31, 39, 39, 39, 39, 39, 39, 39, 39, 39, 39, 39, 39, 39, 39, 39, 39, 39, 39, 39, 39],
         "height":10,
         "id":1,
         "name":"wall_layer",
         "opacity":1,
         "type":"tilelayer",
         "visible":true,
         "width":20,
         "x":0,
         "y":0
        }, 
        {
         "data":[0, 0, 0, 0, 0, 0, 0, 0, 0, 0, 0, 0, 0, 0, 0, 0, 0, 0, 0, 0, 0, 0, 0, 0, 0, 0, 0, 0, 0, 0, 0, 0, 0, 0, 0, 0, 0, 0, 0, 0, 0, 0, 0, 0, 0, 0, 0, 0, 0, 0, 0, 0, 0, 0, 0, 0, 0, 0, 0, 0, 0, 0, 0, 0, 0, 0, 0, 0, 0, 0, 0, 0, 0, 0, 0, 0, 0, 0, 0, 0, 0, 0, 0, 0, 0, 0, 0, 0, 0, 0, 0, 0, 0, 0, 0, 0, 0, 0, 0, 0, 31, 32, 0, 0, 0, 0, 0, 0, 0, 0, 2147483673, 0, 0, 0, 0, 25, 0, 0, 0, 0, 26, 27, 27, 0, 0, 0, 0, 0, 0, 0, 0, 0, 0, 0, 0, 0, 0, 0, 0, 0, 34, 34, 27, 27, 0, 0, 0, 0, 0, 0, 0, 0, 0, 0, 0, 0, 0, 0, 0, 0, 0, 0, 0, 0, 0, 0, 0, 0, 0, 0, 0, 0, 0, 0, 0, 0, 0, 0, 0, 0, 0, 0, 0, 0, 0, 0, 0, 0, 0, 0, 0, 0, 0, 0, 0, 0, 0, 0, 0, 0],
         "height":10,
         "id":3,
         "name":"fg_layer",
         "opacity":1,
         "type":"tilelayer",
         "visible":true,
         "width":20,
         "x":0,
         "y":0
        }, 
        {
         "draworder":"topdown",
         "id":7,
         "name":"text_layer",
         "objects":[
                {
                 "height":18.8438,
                 "id":15,
                 "name":"",
                 "rotation":0,
                 "text":
                    {
                     "text":"Exit",
                     "wrap":true
                    },
                 "type":"",
                 "visible":true,
                 "width":28.0707,
                 "x":11.8193,
                 "y":103.189
                }, 
                {
                 "height":18.8438,
                 "id":16,
                 "name":"",
                 "rotation":0,
                 "text":
                    {
                     "text":"Team",
                     "wrap":true
                    },
                 "type":"",
                 "visible":true,
                 "width":46.4562,
                 "x":186.481898592359,
                 "y":92.8475966676242
                }, 
                {
                 "height":18.84375,
                 "id":19,
                 "name":"",
                 "rotation":0,
                 "text":
                    {
                     "text":"Red",
                     "wrap":true
                    },
                 "type":"",
                 "visible":true,
                 "width":30.3688460571675,
                 "x":156.030745026573,
                 "y":107.211276393278
                }, 
                {
                 "height":18.8438,
                 "id":20,
                 "name":"",
                 "rotation":0,
                 "text":
                    {
                     "text":"Blue",
                     "wrap":true
                    },
                 "type":"",
                 "visible":true,
                 "width":34.965180350474,
                 "x":227.849211031313,
                 "y":108.360346480896
                }],
         "opacity":1,
         "type":"objectgroup",
         "visible":true,
         "x":0,
         "y":0
        }],
 "nextlayerid":8,
 "nextobjectid":22,
 "orientation":"orthogonal",
 "renderorder":"right-down",
 "tiledversion":"1.7.0",
 "tileheight":16,
 "tilesets":[
        {
         "columns":8,
         "firstgid":1,
         "image":"forestTileSet.png",
         "imageheight":96,
         "imagewidth":128,
         "margin":0,
         "name":"forestTileSet",
         "spacing":0,
         "tilecount":48,
         "tileheight":16,
         "tiles":[
                {
                 "id":0,
                 "objectgroup":
                    {
                     "draworder":"index",
                     "id":2,
                     "name":"",
                     "objects":[
                            {
                             "height":16,
                             "id":1,
                             "name":"",
                             "rotation":0,
                             "type":"",
                             "visible":true,
                             "width":16,
                             "x":0,
                             "y":0
                            }],
                     "opacity":1,
                     "type":"objectgroup",
                     "visible":true,
                     "x":0,
                     "y":0
                    }
                }, 
                {
                 "id":1,
                 "objectgroup":
                    {
                     "draworder":"index",
                     "id":2,
                     "name":"",
                     "objects":[
                            {
                             "height":16,
                             "id":1,
                             "name":"",
                             "rotation":0,
                             "type":"",
                             "visible":true,
                             "width":16,
                             "x":0,
                             "y":0
                            }],
                     "opacity":1,
                     "type":"objectgroup",
                     "visible":true,
                     "x":0,
                     "y":0
                    }
                }, 
                {
                 "id":2,
                 "objectgroup":
                    {
                     "draworder":"index",
                     "id":2,
                     "name":"",
                     "objects":[
                            {
                             "height":16,
                             "id":1,
                             "name":"",
                             "rotation":0,
                             "type":"",
                             "visible":true,
                             "width":16,
                             "x":0,
                             "y":0
                            }],
                     "opacity":1,
                     "type":"objectgroup",
                     "visible":true,
                     "x":0,
                     "y":0
                    }
                }, 
                {
                 "id":21,
                 "objectgroup":
                    {
                     "draworder":"index",
                     "id":2,
                     "name":"",
                     "objects":[
                            {
                             "height":16,
                             "id":1,
                             "name":"",
                             "rotation":0,
                             "type":"",
                             "visible":true,
                             "width":16,
                             "x":0,
                             "y":0
                            }],
                     "opacity":1,
                     "type":"objectgroup",
                     "visible":true,
                     "x":0,
                     "y":0
                    }
                }, 
                {
                 "id":29,
                 "objectgroup":
                    {
                     "draworder":"index",
                     "id":2,
                     "name":"",
                     "objects":[
                            {
                             "height":16,
                             "id":1,
                             "name":"",
                             "rotation":0,
                             "type":"",
                             "visible":true,
                             "width":16,
                             "x":0,
                             "y":0
                            }],
                     "opacity":1,
                     "type":"objectgroup",
                     "visible":true,
                     "x":0,
                     "y":0
                    }
                }, 
                {
                 "id":30,
                 "objectgroup":
                    {
                     "draworder":"index",
                     "id":2,
                     "name":"",
                     "objects":[
                            {
                             "height":16,
                             "id":1,
                             "name":"",
                             "rotation":0,
                             "type":"",
                             "visible":true,
                             "width":16,
                             "x":0,
                             "y":0
                            }],
                     "opacity":1,
                     "type":"objectgroup",
                     "visible":true,
                     "x":0,
                     "y":0
                    }
                }, 
                {
                 "id":31,
                 "objectgroup":
                    {
                     "draworder":"index",
                     "id":2,
                     "name":"",
                     "objects":[
                            {
                             "height":16,
                             "id":1,
                             "name":"",
                             "rotation":0,
                             "type":"",
                             "visible":true,
                             "width":16,
                             "x":0,
                             "y":0
                            }],
                     "opacity":1,
                     "type":"objectgroup",
                     "visible":true,
                     "x":0,
                     "y":0
                    }
                }, 
                {
                 "id":37,
                 "objectgroup":
                    {
                     "draworder":"index",
                     "id":2,
                     "name":"",
                     "objects":[
                            {
                             "height":16,
                             "id":1,
                             "name":"",
                             "rotation":0,
                             "type":"",
                             "visible":true,
                             "width":16,
                             "x":0,
                             "y":0
                            }],
                     "opacity":1,
                     "type":"objectgroup",
                     "visible":true,
                     "x":0,
                     "y":0
                    }
                }, 
                {
                 "id":38,
                 "objectgroup":
                    {
                     "draworder":"index",
                     "id":2,
                     "name":"",
                     "objects":[
                            {
                             "height":16,
                             "id":1,
                             "name":"",
                             "rotation":0,
                             "type":"",
                             "visible":true,
                             "width":16,
                             "x":0,
                             "y":0
                            }],
                     "opacity":1,
                     "type":"objectgroup",
                     "visible":true,
                     "x":0,
                     "y":0
                    }
                }, 
                {
                 "id":39,
                 "objectgroup":
                    {
                     "draworder":"index",
                     "id":2,
                     "name":"",
                     "objects":[
                            {
                             "height":16,
                             "id":1,
                             "name":"",
                             "rotation":0,
                             "type":"",
                             "visible":true,
                             "width":16,
                             "x":0,
                             "y":0
                            }],
                     "opacity":1,
                     "type":"objectgroup",
                     "visible":true,
                     "x":0,
                     "y":0
                    }
                }],
         "tilewidth":16
        }],
 "tilewidth":16,
 "type":"map",
 "version":"1.6",
 "width":20
}